{
  "parent": "l2archery:archery/void_bow",
  "criteria": {
    "0": {
      "conditions": {
        "items": [
          {
            "items": [
              "l2archery:void_arrow"
            ]
          }
        ]
      },
      "trigger": "minecraft:inventory_changed"
    }
  },
  "display": {
    "announce_to_chat": true,
    "description": {
      "translate": "advancements.l2archery.advancements.archery.void_arrow.description"
    },
    "frame": "challenge",
    "hidden": false,
    "icon": {
      "item": "l2archery:void_arrow"
    },
    "show_toast": true,
    "title": {
      "translate": "advancements.l2archery.advancements.archery.void_arrow.title"
    }
  },
  "requirements": [
    [
      "0"
    ]
  ]
}