{
  "parent": "l2archery:archery/master_bow",
  "criteria": {
    "0": {
      "conditions": {
        "items": [
          {
            "items": "l2archery:flame_bow"
          }
        ]
      },
      "trigger": "minecraft:inventory_changed"
    }
  },
  "display": {
    "description": {
      "translate": "advancements.l2archery.archery.flame_bow.description"
    },
    "icon": {
      "count": 1,
      "id": "l2archery:flame_bow"
    },
    "title": {
      "translate": "advancements.l2archery.archery.flame_bow.title"
    }
  },
  "requirements": [
    [
      "0"
    ]
  ],
  "sends_telemetry_event": true
}